helpers/__init__.py
helpers/logger.py
pytest_cleanuptotal/__init__.py
pytest_cleanuptotal/cleanup.py
pytest_cleanuptotal/cleanuptotal.py
test/__init__.py
test/conftest.py
test/test_cleanuptest.py
pytest_cleanuptotal-0.3.6.dist-info/LICENSE
pytest_cleanuptotal-0.3.6.dist-info/METADATA
pytest_cleanuptotal-0.3.6.dist-info/WHEEL
pytest_cleanuptotal-0.3.6.dist-info/entry_points.txt
pytest_cleanuptotal-0.3.6.dist-info/top_level.txt
pytest_cleanuptotal-0.3.6.dist-info/RECORD
