Metadata-Version: 2.1
Name: pytest-cleanuptotal
Version: 0.3.6
Summary: A cleanup plugin for pytest
Home-page: https://github.com/tzurp/pytest_cleanuptotal
Author: Tzur Paldi
Author-email: tzur.paldi@outlook.com
Maintainer: Tzur Paldi
Maintainer-email: tzur.paldi@outlook.com
License: MIT
Classifier: Development Status :: 5 - Production/Stable
Classifier: Framework :: Pytest
License-File: LICENSE
